tai_chi_engine/__init__.py
tai_chi_engine/stateful.py
tai_chi_engine/tai_chi.py
tai_chi_engine/teacher.py
tai_chi_engine/trained.py
tai_chi_engine/utils.py
tai_chi_engine/app/__init__.py
tai_chi_engine/app/streamlit/__init__.py
tai_chi_engine/app/streamlit/run.py
tai_chi_engine/app/streamlit/start_app.py
tai_chi_engine/enrich/__init__.py
tai_chi_engine/enrich/basic.py
tai_chi_engine/enrich/file.py
tai_chi_engine/model/__init__.py
tai_chi_engine/model/entry/__init__.py
tai_chi_engine/model/entry/basic.py
tai_chi_engine/model/entry/category.py
tai_chi_engine/model/entry/image.py
tai_chi_engine/model/entry/text.py
tai_chi_engine/model/exit/__init__.py
tai_chi_engine/model/exit/basic.py
tai_chi_engine/model/exit/category.py
tai_chi_engine/model/exit/loss.py
tai_chi_engine/model/exit/metric.py
tai_chi_engine/quantify/__init__.py
tai_chi_engine/quantify/basic.py
tai_chi_engine/static/README.md
tai_chi_engine/static/img/README.md
tai_chi_engine/static/img/multi_category.jpg
tai_chi_engine/static/img/single_category.jpg
tai_chi_engine/static/teacher/README.md
tai_chi_engine/static/teacher/image_quantify.html
tai_chi_engine/static/teacher/multi_category.html
tai_chi_engine/static/teacher/single_category.html
tai_chi_engine/static/teacher/text.html
tai_chi_engine-0.1.3.dist-info/LICENSE
tai_chi_engine-0.1.3.dist-info/METADATA
tai_chi_engine-0.1.3.dist-info/WHEEL
tai_chi_engine-0.1.3.dist-info/top_level.txt
tai_chi_engine-0.1.3.dist-info/RECORD
