Metadata-Version: 2.1
Name: tai-chi-engine
Version: 0.1.3
Summary: UNKNOWN
Home-page: https://github.com/tcengine/tai-chi
License: GPLv3+
Project-URL: Documentation, https://tai-chi-engine.readthedocs.io/
Project-URL: Tracker, https://github.com/tcengine/tai-chi/issues
Platform: UNKNOWN
Classifier: Development Status :: 3 - Alpha
Classifier: Intended Audience :: End Users/Desktop
Classifier: License :: OSI Approved :: GNU General Public License v3 (GPLv3)
Classifier: Natural Language :: English
Classifier: Programming Language :: Python :: 3.6
Classifier: Programming Language :: Python :: 3.7
Classifier: Programming Language :: Python :: 3.8
Classifier: Programming Language :: Python :: 3.9
Classifier: Programming Language :: Python :: 3.10
Requires-Python: >=3.6
License-File: LICENSE
Requires-Dist: category (>=0.1.0)
Requires-Dist: tai-chi-tuna
Requires-Dist: transformers (>=4.15.0)
Requires-Dist: streamlit (>=1.3.1)
Requires-Dist: torchvision (>=0.10.1)
